setup.py
wsk/__init__.py
wsk/wsk.py
wsk.egg-info/PKG-INFO
wsk.egg-info/SOURCES.txt
wsk.egg-info/dependency_links.txt
wsk.egg-info/requires.txt
wsk.egg-info/top_level.txt