Metadata-Version: 1.0
Name: wsk
Version: 0.1.9
Summary: A light wrapper for LexisNexis's Web Services Kit API
Home-page: https://github.com/YaleDHLab/lexis-nexis-wsk
Author: Douglas Duhaime
Author-email: douglas.duhaime@gmail.com
License: MIT
Platform: UNKNOWN
